{"title":"secretary Salazar Announces Recovery Act Funds to Upgrade Earthquake Networks","status":"1","comment":"0","promote":"0","sticky":"0","body":{"und":[{"value":"<p>SAN FRANCISCO, CA &ndash; Secretary of the Interior Ken Salazar today announced the U.S. Geological Survey will fund $29.4 million in earthquake network upgrades nationwide through the American Recovery and Reinvestment Act of 2009, an investment that will significantly improve the timely delivery of information to high-hazard regions such as the Bay area.<\/p>","summary":null,"format":null}]},"field_images":[],"regions":["Oregon","Washington","California","Alaska"],"country":["United States of America"],"mm_tags":["earthquakes","geology","","Recovery","Recovery","Salazar"],"article_type":["Department of Interior"],"release_date":{"und":[{"value":"1239854400","timezone":"UTC","timezone_db":"UTC","date_type":"datestamp"}]},"contacts":{"und":[{"tid":"169087"}]},"subtitle":{"und":[{"value":"","format":null,"safe_value":""}]}}