{"title":"New WWW Site Features USGS Mapping Product Availability","status":"1","comment":"0","promote":"0","sticky":"0","body":{"und":[{"value":"<p>See at a glance where selected USGS mapping products are available. A<!--introstart--> new USGS World Wide Web (WWW) site now provides online maps showing the available geographic coverage for selected digital and aerial photography products.<!--introend--> Check the new site by going to \"Status Graphics: Availability of USGS Geospatial Data and Aerial Photography Products\" <a href=\"http:\/\/mapping.usgs.gov\/www\/products\/status.html\">http:\/\/mapping.usgs.gov\/www\/products\/status.html<\/a>. \n<p>Availability status for digital elevation models, digital line graphs, digital raster graphics, digital orthophoto quadrangles, and aerial photographs can be viewed directly. For some of the products, high-quality page- sized status graphics can be downloaded and saved for later viewing and printing. \r\n<p>Each status graphic page shows a national or single-state view, depending on the product. This WWW site also links customers directly to pages where products can be purchased or downloaded, as well as to search tools, such as the Global Land Information System, that provide access to map and image product inventories. \r\n<p>For information on other mapping products and services visit <a href=\"http:\/\/mapping.usgs.gov\">http:\/\/mapping.usgs.gov<\/a>.<\/p>","summary":null,"format":null}]},"field_images":[],"country":["United States of America"],"mm_tags":[""],"article_type":["National News Release"],"release_date":{"und":[{"value":"894600000","timezone":"UTC","timezone_db":"UTC","date_type":"datestamp"}]},"contacts":{"und":[{"tid":"169684"}]},"subtitle":{"und":[{"value":"","format":null,"safe_value":""}]}}