{"title":"Atmospheric River Slams Northern California","status":"1","comment":"0","promote":"0","sticky":"0","body":{"und":[{"value":"<p><!--introstart-->As people in northern California begin to assess damage from the high winds and heavy rain of October 13 and 14, they may wonder what hit them.<!--introend--> &nbsp;The answer, according to Dave Reynolds, meteorologist-in-charge at NOAA's National Weather Service forecast office in Monterey, was an ","summary":null,"format":null}]},"field_images":[],"regions":["California"],"country":["United States of America"],"mm_tags":["hazard","storm","erosion","landslide","floods","debris","flow","environment"],"article_type":["State News Release"],"release_date":{"und":[{"value":"1255579200","timezone":"UTC","timezone_db":"UTC","date_type":"datestamp"}]},"contacts":{"und":[{"tid":"169129"}]},"subtitle":{"und":[{"value":"","format":null,"safe_value":""}]}}